nvidia_docker_smi/__init__.py
nvidia_docker_smi/cli.py
nvidia_docker_smi-0.1.0.dist-info/licenses/LICENSE
nvidia_docker_smi-0.1.0.dist-info/METADATA
nvidia_docker_smi-0.1.0.dist-info/WHEEL
nvidia_docker_smi-0.1.0.dist-info/entry_points.txt
nvidia_docker_smi-0.1.0.dist-info/top_level.txt
nvidia_docker_smi-0.1.0.dist-info/RECORD
