Metadata-Version: 2.4
Name: nvidia-docker-smi
Version: 0.1.0
Summary: A tool to monitor NVIDIA GPU usage across Docker containers
Author-email: Caleb Chong <lego_0603@hotmail.com>
License-Expression: MIT
Project-URL: Homepage, https://github.com/ThePaperFish/nvidia-docker-smi
Project-URL: Issues, https://github.com/ThePaperFish/nvidia-docker-smi/issues
Classifier: Programming Language :: Python :: 3
Classifier: Operating System :: OS Independent
Requires-Python: >=3.6
License-File: LICENSE
Dynamic: license-file
